pymathics/natlang/__init__.py
pymathics/natlang/linguistic_data.py
pymathics/natlang/manipulate.py
pymathics/natlang/nltk.py
pymathics/natlang/normalization.py
pymathics/natlang/spacy.py
pymathics/natlang/textual_analysis.py
pymathics/natlang/translation.py
pymathics/natlang/util.py
pymathics/natlang/version.py
pymathics_natlang-8.0.0.dist-info/LICENSE
pymathics_natlang-8.0.0.dist-info/METADATA
pymathics_natlang-8.0.0.dist-info/WHEEL
pymathics_natlang-8.0.0.dist-info/top_level.txt
pymathics_natlang-8.0.0.dist-info/RECORD
