Metadata-Version: 2.1
Name: pymathics-natlang
Version: 8.0.0
Maintainer: Mathics3 Group
Maintainer-email: rb@dustyfeet.com
Classifier: Intended Audience :: Developers
Classifier: Intended Audience :: Science/Research
Classifier: License :: OSI Approved :: GNU General Public License v3 (GPLv3)
Classifier: Programming Language :: Python
Classifier: Programming Language :: Python :: 3.8
Classifier: Programming Language :: Python :: 3.9
Classifier: Programming Language :: Python :: 3.10
Classifier: Programming Language :: Python :: 3.11
Classifier: Programming Language :: Python :: 3.12
Classifier: Programming Language :: Python :: Implementation :: CPython
Classifier: Programming Language :: Python :: Implementation :: PyPy
Classifier: Topic :: Scientific/Engineering
Classifier: Topic :: Scientific/Engineering :: Mathematics
Classifier: Topic :: Scientific/Engineering :: Physics
Classifier: Topic :: Software Development :: Interpreters
Classifier: Topic :: Scientific/Engineering :: Human Machine Interfaces
Classifier: Topic :: Text Processing
Classifier: Topic :: Text Processing :: Linguistic
License-File: LICENSE
Requires-Dist: Mathics3>=8.0.0
Requires-Dist: click>=8.0
Requires-Dist: joblib>=1.0.1
Requires-Dist: langid
Requires-Dist: llvmlite>=0.36
Requires-Dist: nltk>=3.8.0
Requires-Dist: PatternLite
Requires-Dist: pyenchant>=3.2.0
Requires-Dist: pycountry>=3.2.0
Requires-Dist: spacy>=3.4
Requires-Dist: wasabi<1.1.0,>=0.8.2
